retroforth/__init__.py
retroforth/retroforth.py
retroforth-2021.1.dist-info/LICENSE
retroforth-2021.1.dist-info/METADATA
retroforth-2021.1.dist-info/WHEEL
retroforth-2021.1.dist-info/top_level.txt
retroforth-2021.1.dist-info/RECORD
