Metadata-Version: 2.1
Name: retroforth
Version: 2021.1
Summary: RetroForth is a modern, pragmatic Forth
Home-page: http://forthworks.com/retro
Author: Charles Childers
Author-email: crc@forthworks.com
License: UNKNOWN
Platform: UNKNOWN
Classifier: Programming Language :: Python :: 3
Classifier: License :: OSI Approved :: ISC License (ISCL)
Classifier: Operating System :: OS Independent
Requires-Python: >=3.6
